MANIFEST.in
README.rst
setup.py
aliyunsdkcms/__init__.py
aliyunsdkcms/request/__init__.py
aliyunsdkcms/request/v20180308/AccessKeyGetRequest.py
aliyunsdkcms/request/v20180308/AddMyGroupInstancesRequest.py
aliyunsdkcms/request/v20180308/CreateAlarmRequest.py
aliyunsdkcms/request/v20180308/CreateMyGroupsRequest.py
aliyunsdkcms/request/v20180308/CreateNotifyPolicyRequest.py
aliyunsdkcms/request/v20180308/CreateTaskRequest.py
aliyunsdkcms/request/v20180308/DeleteAlarmRequest.py
aliyunsdkcms/request/v20180308/DeleteCustomMetricRequest.py
aliyunsdkcms/request/v20180308/DeleteMyGroupInstancesRequest.py
aliyunsdkcms/request/v20180308/DeleteMyGroupsRequest.py
aliyunsdkcms/request/v20180308/DeleteNotifyPolicyRequest.py
aliyunsdkcms/request/v20180308/DeleteTasksRequest.py
aliyunsdkcms/request/v20180308/DescribeAlarmHistoryRequest.py
aliyunsdkcms/request/v20180308/DescribeContactRequest.py
aliyunsdkcms/request/v20180308/DescribeISPAreaCityRequest.py
aliyunsdkcms/request/v20180308/DescribeTaskDetailRequest.py
aliyunsdkcms/request/v20180308/DescribeTasksRequest.py
aliyunsdkcms/request/v20180308/DisableActiveAlertRequest.py
aliyunsdkcms/request/v20180308/DisableAlarmRequest.py
aliyunsdkcms/request/v20180308/EnableActiveAlertRequest.py
aliyunsdkcms/request/v20180308/EnableAlarmRequest.py
aliyunsdkcms/request/v20180308/GetContactsRequest.py
aliyunsdkcms/request/v20180308/GetMyGroupsRequest.py
aliyunsdkcms/request/v20180308/GetNotifyPolicyRequest.py
aliyunsdkcms/request/v20180308/ListActiveAlertRuleRequest.py
aliyunsdkcms/request/v20180308/ListAlarmHistoryRequest.py
aliyunsdkcms/request/v20180308/ListAlarmRequest.py
aliyunsdkcms/request/v20180308/ListContactGroupRequest.py
aliyunsdkcms/request/v20180308/ListMyGroupCategoriesRequest.py
aliyunsdkcms/request/v20180308/ListMyGroupInstancesDetailsRequest.py
aliyunsdkcms/request/v20180308/ListMyGroupInstancesRequest.py
aliyunsdkcms/request/v20180308/ListMyGroupsRequest.py
aliyunsdkcms/request/v20180308/ListNotifyPolicyRequest.py
dd_aliyun_python_sdk_cms.egg-info/PKG-INFO
dd_aliyun_python_sdk_cms.egg-info/SOURCES.txt
dd_aliyun_python_sdk_cms.egg-info/dependency_links.txt
dd_aliyun_python_sdk_cms.egg-info/requires.txt
dd_aliyun_python_sdk_cms.egg-info/top_level.txt